fractalplots/__init__.py
fractalplots/base.py
fractalplots/julia.py
fractalplots/koch.py
fractalplots/lsystem.py
fractalplots/mandelbrot.py
fractalplots/sierpinski.py
fractalplots-0.1.2.dist-info/licenses/LICENSE
fractalplots-0.1.2.dist-info/METADATA
fractalplots-0.1.2.dist-info/WHEEL
fractalplots-0.1.2.dist-info/top_level.txt
fractalplots-0.1.2.dist-info/RECORD
