Metadata-Version: 2.4
Name: fractalplots
Version: 0.1.2
Summary: Generate and visualize fractal patterns like Mandelbrot, Julia, Koch, Sierpinski, and L-Systems.
Author: Your Name
Author-email: Bhavy Khatri <bhavykhatri@gmail.com>
License-Expression: MIT
Project-URL: Homepage, https://github.com/bhavykhatri/fractalplots
Project-URL: Source, https://github.com/bhavykhatri/fractalplots
Project-URL: Tracker, https://github.com/bhavykhatri/fractalplots/issues
Keywords: fractal,math,visualization,mandelbrot,julia,koch,sierpinski,l-system
Classifier: Development Status :: 3 - Alpha
Classifier: Intended Audience :: Science/Research
Classifier: Intended Audience :: Developers
Classifier: Programming Language :: Python :: 3
Classifier: Programming Language :: Python :: 3.7
Classifier: Programming Language :: Python :: 3.8
Classifier: Programming Language :: Python :: 3.9
Classifier: Programming Language :: Python :: 3.10
Classifier: Topic :: Scientific/Engineering :: Visualization
Classifier: Topic :: Software Development :: Libraries :: Python Modules
Requires-Python: >=3.7
License-File: LICENSE
Requires-Dist: numpy>=1.21
Requires-Dist: matplotlib>=3.4
Dynamic: author
Dynamic: license-file
Dynamic: requires-python
